django_markdown_renderer-0.2.0.dist-info/licenses/LICENSE
markdown_renderer/__init__.py
markdown_renderer/admin.py
markdown_renderer/apps.py
markdown_renderer/models.py
markdown_renderer/tests.py
markdown_renderer/urls.py
markdown_renderer/views.py
markdown_renderer/migrations/__init__.py
markdown_renderer/templates/markdown_renderer/index.html
markdown_site/__init__.py
markdown_site/asgi.py
markdown_site/settings.py
markdown_site/urls.py
markdown_site/wsgi.py
django_markdown_renderer-0.2.0.dist-info/METADATA
django_markdown_renderer-0.2.0.dist-info/WHEEL
django_markdown_renderer-0.2.0.dist-info/top_level.txt
django_markdown_renderer-0.2.0.dist-info/RECORD
